mynameisleamcharoen
